scrapy_pagestorage.py
scrapy_pagestorage-0.4.0.dist-info/LICENSE
scrapy_pagestorage-0.4.0.dist-info/METADATA
scrapy_pagestorage-0.4.0.dist-info/WHEEL
scrapy_pagestorage-0.4.0.dist-info/top_level.txt
scrapy_pagestorage-0.4.0.dist-info/RECORD
