Metadata-Version: 2.1
Name: scrapy-pagestorage
Version: 0.4.0
Summary: Scrapy extension to store info in storage service
Home-page: https://github.com/scrapy-plugins/scrapy-pagestorage
Author: Scrapy developers
Author-email: opensource@scrapinghub.com
License: BSD
Platform: Any
Classifier: Development Status :: 5 - Production/Stable
Classifier: License :: OSI Approved :: BSD License
Classifier: Operating System :: OS Independent
Classifier: Programming Language :: Python
Classifier: Programming Language :: Python :: 3
Classifier: Programming Language :: Python :: 3.5
Classifier: Programming Language :: Python :: 3.6
Classifier: Programming Language :: Python :: 3.7
Classifier: Programming Language :: Python :: 3.8
Classifier: Programming Language :: Python :: 3.9
Classifier: Programming Language :: Python :: 3.10
Requires-Python: >=3.5
License-File: LICENSE
Requires-Dist: Scrapy (>=1.0.3)
Requires-Dist: scrapinghub (>=1.9.0)
Requires-Dist: scrapinghub-entrypoint-scrapy (>=0.4)
